ErrorSearcher/__init__.py
ErrorSearcher-1.0.1.dist-info/LICENSE
ErrorSearcher-1.0.1.dist-info/METADATA
ErrorSearcher-1.0.1.dist-info/WHEEL
ErrorSearcher-1.0.1.dist-info/top_level.txt
ErrorSearcher-1.0.1.dist-info/RECORD
