Metadata-Version: 2.1
Name: ErrorSearcher
Version: 1.0.1
Summary: ErrorSearcher help to search error on webbrowser
Home-page: https://github.com/sachin11226/ErrorSearcher
Author: Sachin
Author-email: sachin1122621003@gmail.com
License: MIT
Download-URL: https://github.com/sachin11226/ErrorSearcher/archive/1.0.2.tar.gz
Project-URL: Bug Tracker, https://github.com/sachin11226/ErrorSearcher/issues
Keywords: python,error,ErrorSearcher,file,python3
Platform: any
Classifier: Programming Language :: Python :: 3
Classifier: License :: OSI Approved :: MIT License
Classifier: Operating System :: OS Independent
License-File: LICENSE
